{
  "type": "minecraft:crafting_shaped",
  "category": "misc",
  "key": {
    "1": {
      "item": "l2hostility:slowness"
    },
    "2": {
      "item": "l2hostility:freezing"
    },
    "A": {
      "item": "l2hostility:killer_aura"
    },
    "B": {
      "item": "l2complements:blackstone_core"
    },
    "I": {
      "item": "l2hostility:chaos_ingot"
    }
  },
  "pattern": [
    "BAB",
    "1I2",
    "BAB"
  ],
  "result": {
    "item": "l2hostility:ring_of_incarceration"
  },
  "show_notification": true
}